LICENSE
MANIFEST.in
README
README.rst
setup.cfg
setup.py
src/clik_shell.py
src/clik_shell.egg-info/PKG-INFO
src/clik_shell.egg-info/SOURCES.txt
src/clik_shell.egg-info/dependency_links.txt
src/clik_shell.egg-info/not-zip-safe
src/clik_shell.egg-info/requires.txt
src/clik_shell.egg-info/top_level.txt